AUTHORS.txt
CHANGES.txt
INSTALL.txt
LICENSE.txt
MANIFEST.in
README.rst
TODO.txt
development.ini
production.ini
setup.cfg
setup.py
tox.ini
anuket/__init__.py
anuket/security.py
anuket/subscribers.py
anuket.egg-info/PKG-INFO
anuket.egg-info/SOURCES.txt
anuket.egg-info/dependency_links.txt
anuket.egg-info/entry_points.txt
anuket.egg-info/not-zip-safe
anuket.egg-info/requires.txt
anuket.egg-info/top_level.txt
anuket/lib/__init__.py
anuket/lib/alembic_utils.py
anuket/lib/i18n.py
anuket/lib/validators.py
anuket/locale/en/LC_MESSAGES/anuket.mo
anuket/locale/fr/LC_MESSAGES/anuket.mo
anuket/models/__init__.py
anuket/models/auth.py
anuket/models/migration.py
anuket/models/rootfactory.py
anuket/scripts/__init__.py
anuket/scripts/backupdb.py
anuket/scripts/initializedb.py
anuket/scripts/upgradedb.py
anuket/scripts/alembic/README.txt
anuket/scripts/alembic/script.py.mako
anuket/scripts/alembic/versions/README.txt
anuket/static/css/bootstrap-responsive.css
anuket/static/css/bootstrap-responsive.min.css
anuket/static/css/bootstrap.css
anuket/static/css/bootstrap.min.css
anuket/static/css/style.css
anuket/static/fonts/raphaelicons-license.txt
anuket/static/fonts/raphaelicons-webfont.svg
anuket/static/fonts/raphaelicons-webfont.ttf
anuket/static/fonts/raphaelicons-webfont.woff
anuket/static/img/anuket.svg
anuket/static/img/favicon.ico
anuket/static/img/pyramid-small.png
anuket/static/js/anuket.js
anuket/static/js/bootstrap.js
anuket/static/js/bootstrap.min.js
anuket/static/js/html5shim.js
anuket/static/js/jquery.min.js
anuket/templates/404.mako
anuket/templates/about.mako
anuket/templates/base.mako
anuket/templates/index.mako
anuket/templates/login.mako
anuket/templates/tools/base.mako
anuket/templates/tools/index.mako
anuket/templates/tools/user/base.mako
anuket/templates/tools/user/password_edit.mako
anuket/templates/tools/user/password_form_fields.mako
anuket/templates/tools/user/user_add.mako
anuket/templates/tools/user/user_edit.mako
anuket/templates/tools/user/user_form_fields.mako
anuket/templates/tools/user/user_list.mako
anuket/templates/tools/user/user_search.mako
anuket/templates/tools/user/user_show.mako
anuket/templates/widgets/confirm_delete.mako
