Metadata-Version: 1.0
Name: anuket
Version: 0.5.2
Summary: Anuket web application
Home-page: http://github.com/lazaret/anuket
Author: LDPL - Laboratoire Départemental de Préhistoire du Lazaret
Author-email: opensource@lazaret.unice.fr
License: Expat licence (or MIT licence)
Keywords: web wsgi pyramid
Platform: UNKNOWN
Classifier: Programming Language :: Python
Classifier: Framework :: Pyramid
Classifier: Topic :: Internet :: WWW/HTTP
Classifier: Topic :: Internet :: WWW/HTTP :: WSGI :: Application
